README.md
setup.py
WaveFlow/__init__.py
WaveFlow/preRequisite/preRequisites.py
WaveFlow/service/data/To.py
WaveFlow/service/data/archive.py
WaveFlow/service/data/handler.py
WaveFlow/service/generate/generator.py
WaveFlow/service/transmite/transmitter.py
WaveFlow/preRequisite/preRequisites.py
WaveFlow/service/data/To.py
WaveFlow/service/data/archive.py
WaveFlow/service/data/handler.py
WaveFlow/service/generate/generator.py
WaveFlow/service/transmite/transmitter.py
wave_flow.egg-info/PKG-INFO
wave_flow.egg-info/SOURCES.txt
wave_flow.egg-info/dependency_links.txt
wave_flow.egg-info/requires.txt
wave_flow.egg-info/top_level.txt