Metadata-Version: 2.1
Name: wave-flow
Version: 1.0.8
Summary: WAVE - Workflow Automation and Versatile Engine
Author: Lucas Lourenço
Author-email: dev.lucaslourenco@gmail.com
License: MIT License
Keywords: wave build docx treatdata xlsx to word waveflow wave-flow
